tam/__init__.py
tam/defs.py
tam-0.1.2.dist-info/DESCRIPTION.rst
tam-0.1.2.dist-info/METADATA
tam-0.1.2.dist-info/RECORD
tam-0.1.2.dist-info/WHEEL
tam-0.1.2.dist-info/metadata.json
tam-0.1.2.dist-info/top_level.txt
