Metadata-Version: 2.0
Name: tam
Version: 0.1.2
Summary: Tile Assembly Model modules
Home-page: https://github.com/luizirber/tam
Author: Luiz Irber
Author-email: tam@luizirber.org
License: BSD
Keywords: tile,assembly,model,modules
Platform: UNKNOWN
Classifier: Development Status :: 1 - Planning
Classifier: Intended Audience :: Developers
Classifier: License :: OSI Approved :: BSD License
Classifier: Operating System :: Unix
Classifier: Operating System :: POSIX
Classifier: Operating System :: Microsoft :: Windows
Classifier: Programming Language :: Python
Classifier: Programming Language :: Python :: 2
Classifier: Programming Language :: Python :: 2.7
Classifier: Programming Language :: Python :: 3
Classifier: Programming Language :: Python :: 3.4
Classifier: Programming Language :: Python :: 3.5
Classifier: Programming Language :: Python :: Implementation :: CPython
Classifier: Topic :: Utilities
Requires-Dist: enum34
Requires-Dist: hypothesis
Requires-Dist: pyrsistent
Requires-Dist: toolz
